pdfconverse/__about__.py
pdfconverse/__init__.py
pdfconverse/gemini.py
pdfconverse/mock_model.py
pdfconverse/models.py
pdfconverse/page.py
pdfconverse/pdfconverse.py
pdfconverse/prompts.py
pdfconverse/validators.py
pdfconverse/formats/gemini_expected_output.py
pdfconverse/interfaces/__init__.py
pdfconverse/interfaces/model.py
pdfconverse/samples/gemini_test_file.pdf
pdfconverse-0.1.3.dist-info/METADATA
pdfconverse-0.1.3.dist-info/WHEEL
pdfconverse-0.1.3.dist-info/licenses/LICENSE.txt
pdfconverse-0.1.3.dist-info/RECORD
