Metadata-Version: 2.3
Name: pdfconverse
Version: 0.1.3
Summary: A tool for interacting with PDF documents using AI, allowing page-specific prompts and summaries. PDFConverse leverages Gemini API to provide intelligent responses to queries about PDF content, optimizing token usage and enabling focused analysis of specific page ranges.
Project-URL: Documentation, https://github.com/prodeveloper/pdfconverse?tab=readme-ov-file
Project-URL: Issues, https://github.com/prodeveloper/pdfconverse/issues
Project-URL: Source, https://github.com/prodeveloper/pdfconverse
Author-email: Chencha Jacob <jmokua@gmail.com>
License-Expression: MIT
License-File: LICENSE.txt
Keywords: ai,document analysis,gemini,pdf,smart reading
Classifier: Development Status :: 4 - Beta
Classifier: Programming Language :: Python
Classifier: Programming Language :: Python :: 3.8
Classifier: Programming Language :: Python :: 3.9
Classifier: Programming Language :: Python :: 3.10
Classifier: Programming Language :: Python :: 3.11
Classifier: Programming Language :: Python :: 3.12
Classifier: Programming Language :: Python :: Implementation :: CPython
Classifier: Programming Language :: Python :: Implementation :: PyPy
Requires-Python: >=3.8
Requires-Dist: google-generativeai
Requires-Dist: pydantic
Requires-Dist: pypdf
Requires-Dist: pytest
Requires-Dist: python-dotenv
